bin/bottle.py
lbox/__init__.py
lbox/common.py
lbox/expirator.py
lbox/webapp.py
lbox/appfiles/__init__.py
lbox/appfiles/css/style.css
lbox/appfiles/html/favicon-32x32.png
lbox/appfiles/html/index.html
lbox/appfiles/js/lbox.js
lbox-2.0.0.dist-info/licenses/LICENSE
lbox-2.0.0.dist-info/METADATA
lbox-2.0.0.dist-info/WHEEL
lbox-2.0.0.dist-info/entry_points.txt
lbox-2.0.0.dist-info/top_level.txt
lbox-2.0.0.dist-info/RECORD
