Metadata-Version: 2.4
Name: lbox
Version: 2.0.0
Summary: Serve files via HTTP for a set duration of time.
Author-email: Javier Llopis <javier@llopis.me>
License-Expression: MIT
Project-URL: Repository, https://github.com/destrangis/lbox
Classifier: Development Status :: 4 - Beta
Classifier: Environment :: Web Environment
Classifier: Framework :: Bottle
Classifier: Intended Audience :: Information Technology
Classifier: Intended Audience :: System Administrators
Classifier: Operating System :: OS Independent
Classifier: Programming Language :: Python :: 3.10
Classifier: Programming Language :: Python :: 3.11
Classifier: Programming Language :: Python :: 3.12
Classifier: Programming Language :: Python :: 3.13
Classifier: Programming Language :: JavaScript
Classifier: Topic :: Communications :: File Sharing
Classifier: Topic :: Internet :: WWW/HTTP :: WSGI :: Application
Requires-Python: >=3.10
License-File: LICENSE
Requires-Dist: bottle
Requires-Dist: bjoern
Dynamic: license-file
